yield_curve_dynamics/__init__.py
yield_curve_dynamics/animate.py
yield_curve_dynamics/cli.py
yield_curve_dynamics/data.py
yield_curve_dynamics/download.py
yield_curve_dynamics/keyrates.py
yield_curve_dynamics/pca.py
yield_curve_dynamics/video.py
yield_curve_dynamics/yield_curve_dynamics.py
yield_curve_dynamics-0.2.0.dist-info/AUTHORS.rst
yield_curve_dynamics-0.2.0.dist-info/LICENSE
yield_curve_dynamics-0.2.0.dist-info/METADATA
yield_curve_dynamics-0.2.0.dist-info/WHEEL
yield_curve_dynamics-0.2.0.dist-info/entry_points.txt
yield_curve_dynamics-0.2.0.dist-info/top_level.txt
yield_curve_dynamics-0.2.0.dist-info/RECORD
