Metadata-Version: 2.1
Name: yield-curve-dynamics
Version: 0.2.0
Summary: A cursory look at the dynamics of zero coupon bond yield curves.
Home-page: https://github.com/luphord/yield_curve_dynamics
Author: luphord
Author-email: luphord@protonmail.com
License: MIT license
Keywords: yield_curve_dynamics
Platform: UNKNOWN
Classifier: Development Status :: 2 - Pre-Alpha
Classifier: Intended Audience :: Developers
Classifier: License :: OSI Approved :: MIT License
Classifier: Natural Language :: English
Classifier: Programming Language :: Python :: 3
Classifier: Programming Language :: Python :: 3.7
Requires-Dist: Click (>=6.0)
Requires-Dist: nelson-siegel-svensson (>=0.3)
Requires-Dist: jupyter (>=1.0)
Requires-Dist: pandas (>=0.24)
Requires-Dist: matplotlib (>=3.0)
Requires-Dist: scikit-learn (>=0.20)
